pyexops/__init__.py
pyexops/astrometry.py
pyexops/atmosphere.py
pyexops/binary_star_system.py
pyexops/exovisualizer.py
pyexops/orbital_solver.py
pyexops/photometer.py
pyexops/planet.py
pyexops/scene.py
pyexops/simulator.py
pyexops/star.py
pyexops/visualizer.py
pyexops-0.1.39.dist-info/METADATA
pyexops-0.1.39.dist-info/WHEEL
pyexops-0.1.39.dist-info/top_level.txt
pyexops-0.1.39.dist-info/RECORD
